{
  "nid": "2_367",
  "title": "Angiodysplasia",
  "body_html": "<div>Angiodysplasia is a vascular deformity of the gastrointestinal tract which predisposes to bleeding and iron deficiency anaemia. There is thought to be an association with aortic stenosis, although this is debated. Angiodysplasia is generally seen in elderly patients<br /><br />Diagnosis<br /><ul><li>colonoscopy</li><li>mesenteric angiography if acutely bleeding</li></ul><br />Management<br /><ul><li>endoscopic cautery or argon plasma coagulation</li><li>antifibrinolytics e.g. Tranexamic acid</li><li>oestrogens may also be used</li></ul></div>\n\n<div id=\"mybodylinks\"></div>\n\n<div id=\"mybodymedia\"></div>\n\n\n<div id=\"categorynum\">5</div>\n\n<div id=\"subcategorynum\">200</div>\n\n<div id=\"categoryname\">Pathology</div>\n\n<div id=\"subcategoryname\">GI & endocrine pathology</div>\n<div id=\"mybody\">\n\n<div id=\"body_content\">\nAngiodysplasia is a vascular deformity of the gastrointestinal tract which predisposes to bleeding and iron deficiency anaemia. There is thought to be an association with aortic stenosis, although this is debated. Angiodysplasia is generally seen in elderly patients<br /><br />Diagnosis<br /><ul><li>colonoscopy</li><li>mesenteric angiography if acutely bleeding</li></ul><br />Management<br /><ul><li>endoscopic cautery or argon plasma coagulation</li><li>antifibrinolytics e.g. Tranexamic acid</li><li>oestrogens may also be used</li></ul></div>\n\n\n<BR><BR><br><br></div>",
  "category": "2",
  "sort_order": 7,
  "related_nids": [
    "1_2463",
    "2_150",
    "2_524",
    "1_2751",
    "2_325"
  ]
}